mkdocs_git_revision_date_plugin/__init__.py
mkdocs_git_revision_date_plugin/plugin.py
mkdocs_git_revision_date_plugin/util.py
mkdocs_git_revision_date_plugin-0.3.1.dist-info/LICENSE
mkdocs_git_revision_date_plugin-0.3.1.dist-info/METADATA
mkdocs_git_revision_date_plugin-0.3.1.dist-info/WHEEL
mkdocs_git_revision_date_plugin-0.3.1.dist-info/entry_points.txt
mkdocs_git_revision_date_plugin-0.3.1.dist-info/top_level.txt
mkdocs_git_revision_date_plugin-0.3.1.dist-info/RECORD
